gitlab_release_notes_generator.py
gitlab_release_notes_generator-1.3.0.dist-info/METADATA
gitlab_release_notes_generator-1.3.0.dist-info/WHEEL
gitlab_release_notes_generator-1.3.0.dist-info/entry_points.txt
gitlab_release_notes_generator-1.3.0.dist-info/top_level.txt
gitlab_release_notes_generator-1.3.0.dist-info/RECORD
