Metadata-Version: 2.1
Name: gitlab-release-notes-generator
Version: 1.3.0
Summary: Utility for use in gitlab ci to generate changelogs.
Home-page: https://gitlab.com/nimpsch/gitlab_release_notes_generator.git
Author: Sebastian Nimpsch
Author-email: snimpsch@gmail.com
License: MIT
Requires-Dist: requests
Requires-Dist: python-dateutil
Requires-Dist: setuptools-scm
